unid05_unicass/full-adder/somador.sv
module somador(
	input logic clk,
	input logic A,
	input logic B,
	input logic Cin,

	output logic Sum,
	output logic Cout

);

	always_ff @(posedge clk) begin
		Sum <= A ^ B ^ Cin;
		Cout <= (A&B) | (Cin & (A^B));

	end
endmodule

unid05_unicass/full-adder/somador_tb.sv
module somador_tb;
	logic clk;
	logic A;
	logic B;
	logic Cin;

	logic Sum;
	logic Cout;

// Instancia do Modulo

	somador FA(
		.clk(clk),
		.A(A),
		.B(B),
		.Cin(Cin),
		.Sum(Sum),
		.Cout(Cout)

	);

	//Gerar o clock
	
	always #5 clk = ~clk;

	initial begin
		$dumpfile("test.vcd");
		$dumpvars(0, somador_tb);

	clk = 0;
	A = 0; B = 0; Cin = 0; #10;
	A = 0; B = 0; Cin = 1; #10;
	A = 0; B = 1; Cin = 0; #10;
	A = 0; B = 1; Cin = 1; #10;
	A = 1; B = 0; Cin = 0; #10;
	A = 1; B = 0; Cin = 1; #10;
	A = 1; B = 1; Cin = 0; #10;
	A = 1; B = 1; Cin = 1; #10;

	#20;
	$finish;

end
endmodule

unid05_unicass/aula0603/test.vcd
$date
	Fri Mar  6 14:56:22 2026
$end
$version
	Icarus Verilog
$end
$timescale
	1s
$end
$scope module somador_tb $end
$var wire 1 ! Sum $end
$var wire 1 " Cout $end
$var reg 1 # A $end
$var reg 1 $ B $end
$var reg 1 % Cin $end
$var reg 1 & clk $end
$scope module FA $end
$var wire 1 # A $end
$var wire 1 $ B $end
$var wire 1 % Cin $end
$var wire 1 & clk $end
$var reg 1 " Cout $end
$var reg 1 ! Sum $end
$upscope $end
$upscope $end
$enddefinitions $end
$comment Show the parameter values. $end
$dumpall
$end
#0
$dumpvars
0&
0%
0$
0#
x"
x!
$end
#5
0"
0!
1&
#10
0&
1%
#15
1!
1&
#20
0&
0%
1$
#25
1&
#30
0&
1%
#35
1"
0!
1&
#40
0&
0%
0$
1#
#45
0"
1!
1&
#50
0&
1%
#55
1"
0!
1&
#60
0&
0%
1$
#65
1&
#70
0&
1%
#75
1!
1&
