projetofinal/shared/sram_project/sram.v
`timescale 1ns/1ps

// ======================================================
// SRAM 4x4 WITH CHIP SELECT
// ======================================================

module sram (
    input  wire        clk,
    input  wire        cs,            // Chip Select (ativo alto)
    input  wire        wr_n,          // Write Enable (ativo baixo)
    input  wire        rd_n,          // Output Enable / Read Enable (ativo baixo)

    //Decodificadores Linha e Coluna
    input  wire [1:0]  row_addr,      
    input  wire [1:0]  col_addr,      

    input  wire        data_in,

    output reg         data_out,
    output reg         data_out_bar
);

    reg memory [0:3][0:3];

    integer i, j;

    initial begin
        for (i = 0; i < 4; i = i + 1) begin
            for (j = 0; j < 4; j = j + 1) begin
                memory[i][j] = 1'b0;
            end
        end
    end

    // WRITE OPERATION

    always @(posedge clk) begin

        // CS ativo + WE ativo
        if (cs && !wr_n) begin
            memory[row_addr][col_addr] <= data_in;
        end

    end

    // READ OPERATION

    always @(*) begin

        // CS ativo + OE ativo
        if (cs && !rd_n) begin

            data_out     = memory[row_addr][col_addr];
            data_out_bar = ~memory[row_addr][col_addr];

        end
        else begin

            data_out     = 1'bz;
            data_out_bar = 1'bz;

        end

    end

endmodule

projetofinal/shared/sram_project/sram_tb.v
`timescale 1ns/1ps

// ======================================================
// TESTBENCH - SRAM 4x4
// ======================================================

module tb_sram;

    // =========================
    // ENTRADAS
    // =========================
    reg clk;
    reg cs;
    reg wr_n;
    reg rd_n;

    reg [1:0] row_addr;
    reg [1:0] col_addr;

    reg data_in;

    // =========================
    // SAÍDAS
    // =========================
    wire data_out;
    wire data_out_bar;

    // =========================
    // DUT
    // =========================
    sram dut (
        .clk(clk),
        .cs(cs),
        .wr_n(wr_n),
        .rd_n(rd_n),
        .row_addr(row_addr),
        .col_addr(col_addr),
        .data_in(data_in),
        .data_out(data_out),
        .data_out_bar(data_out_bar)
    );

    // =========================
    // CLOCK
    // =========================
    always #5 clk = ~clk;

    // =========================
    // TESTE
    // =========================
    initial begin

        // waveform
        $dumpfile("sram.vcd");
        $dumpvars(0, tb_sram);

        // inicialização
        clk      = 0;
        cs       = 0;
        wr_n     = 1;
        rd_n     = 1;
        row_addr = 2'b00;
        col_addr = 2'b00;
        data_in  = 0;

        // ==========================================
        // WRITE OPERATION
        // escreve '1' em [1][2]
        // ==========================================
        #10;

        cs       = 1;
        wr_n     = 0;
        rd_n     = 1;

        row_addr = 2'b01;
        col_addr = 2'b10;

        data_in  = 1'b1;

        #10;

        wr_n = 1;

        // ==========================================
        // WRITE OPERATION
        // escreve '0' em [3][0]
        // ==========================================
        #10;

        wr_n     = 0;

        row_addr = 2'b11;
        col_addr = 2'b00;

        data_in  = 1'b0;

        #10;

        wr_n = 1;

        // ==========================================
        // READ [1][2]
        // ==========================================
        #10;

        rd_n     = 0;

        row_addr = 2'b01;
        col_addr = 2'b10;

        #10;

        // ==========================================
        // READ [3][0]
        // ==========================================
        #10;

        row_addr = 2'b11;
        col_addr = 2'b00;

        #10;

        // ==========================================
        // HOLD / IDLE
        // ==========================================
        #10;

        cs   = 0;
        rd_n = 1;

        #20;

        $finish;

    end

endmodule

projetofinal/shared/sram_project/sram.vcd
$date
	Sat May 16 04:10:26 2026
$end
$version
	Icarus Verilog
$end
$timescale
	1ps
$end
$scope module tb_sram $end
$var wire 1 ! data_out_bar $end
$var wire 1 " data_out $end
$var reg 1 # clk $end
$var reg 2 $ col_addr [1:0] $end
$var reg 1 % cs $end
$var reg 1 & data_in $end
$var reg 1 ' rd_n $end
$var reg 2 ( row_addr [1:0] $end
$var reg 1 ) wr_n $end
$scope module dut $end
$var wire 1 # clk $end
$var wire 2 * col_addr [1:0] $end
$var wire 1 % cs $end
$var wire 1 & data_in $end
$var wire 1 ' rd_n $end
$var wire 2 + row_addr [1:0] $end
$var wire 1 ) wr_n $end
$var reg 1 " data_out $end
$var reg 1 ! data_out_bar $end
$var integer 32 , i [31:0] $end
$var integer 32 - j [31:0] $end
$upscope $end
$upscope $end
$enddefinitions $end
$comment Show the parameter values. $end
$dumpall
$end
#0
$dumpvars
b100 -
b100 ,
b0 +
b0 *
1)
b0 (
1'
0&
0%
b0 $
0#
z"
z!
$end
#5000
1#
#10000
0#
1&
b10 $
b10 *
b1 (
b1 +
0)
1%
#15000
1#
#20000
0#
1)
#25000
1#
#30000
0#
0&
b0 $
b0 *
b11 (
b11 +
0)
#35000
1#
#40000
0#
1)
#45000
1#
#50000
0!
1"
0#
b10 $
b10 *
b1 (
b1 +
0'
#55000
1#
#60000
0#
#65000
1#
#70000
1!
0"
0#
b0 $
b0 *
b11 (
b11 +
#75000
1#
#80000
0#
#85000
1#
#90000
z!
z"
0#
1'
0%
